{
  "main": [
    {
      "title": "Accueil",
      "url": "/"
    },
    {
      "title": "Bitcoin",
      "url": "/bitcoin/",
      "children": [
        { "title": "Introduction", "url": "/bitcoin/introduction/" },
        { "title": "Minage", "url": "/bitcoin/minage/" },
        { "title": "Cas d'Usage", "url": "/bitcoin/cas-usage/" },
        { "title": "Impact Environnemental", "url": "/bitcoin/impact-environnemental/" },
        { "title": "Évolution du Prix", "url": "/bitcoin/evolution-prix/" },
        { "title": "Communautés Locales", "url": "/bitcoin/communautes-locales/" }
      ]
    },
    {
      "title": "Guide",
      "url": "/getting-started/",
      "children": [
        {
          "title": "Introduction",
          "url": "/getting-started/introduction-blockchain/"
        },
        {
          "title": "Démarrage",
          "url": "/getting-started/get-started/"
        },
        {
          "title": "Wallets",
          "url": "/wallets/"
        },
        {
          "title": "Sécurisation",
          "url": "/securisation/"
        }
      ]
    },
    {
      "title": "Lightning Network",
      "url": "/lightning-network/",
      "children": [
        { "title": "Bases", "url": "/lightning-network/basics/" },
        { "title": "Canaux", "url": "/lightning-network/channels/" },
        { "title": "Démarrage", "url": "/lightning-network/getting-started/" },
        { "title": "Fonctionnement", "url": "/lightning-network/fonctionnement/" },
        { "title": "Canaux et paiements", "url": "/lightning-network/canaux-et-paiements/" },
        { "title": "Gestion des données", "url": "/manage-data/lightning-network/" },
        { "title": "Nostr Wallet Connect", "url": "/use-data/nostr-wallet-connect/" }
      ]
    },

    {
      "title": "Communauté Token4Good",
      "url": "/token4good/",
      "children": [
        { "title": "Mission et valeurs", "url": "/token4good/mission/" },
        { "title": "Aide aux débutants", "url": "/token4good/aide-debutants/" },
        { "title": "Projets en cours", "url": "/token4good/projets/" },
        { "title": "Guide de contribution", "url": "/token4good/contribuer/" },
        { "title": "Participer", "url": "/token4good/participer/" }
      ]
    },

    {
      "title": "DazBox",
      "url": "/dazbox/",
      "children": [
        { "title": "Démarrage", "url": "/umbrel/getting-started/" },
        { "title": "Applications", "url": "/umbrel/applications/" },
        { "title": "Daznode", "url": "/cas-dusage-daznode/" },
        { "title": "Heuristique", "url": "/rag/heuristic/" },
        { "title": "Introduction", "url": "/rag/introduction/" },
        { "title": "Applications", "url": "/rag/applications/" },
        { "title": "Heuristique", "url": "/rag/heuristic/" },
        { "title": "Analyse", "url": "/rag/analysis/" },
        { "title": "Développeurs", "url": "/devs/" }
      ]
    },


    {
      "title": "",
      "url": "#"
    }, 
    {
      "title": "Glossaire",
      "url": "/glossary/"
    },
    {
      "title": "",
      "url": "#"
    }, 
    {
      "title": "",
      "url": "#"
    },    {
      "title": "",
      "url": "#"
    }, 
    {
      "title": "",
      "url": "#"
    },    {
      "title": "",
      "url": "#"
    }, 
    {
      "title": "",
      "url": "#"
    },    {
      "title": "",
      "url": "#"
    }, 
    {
      "title": "",
      "url": "#"
    },    {
      "title": "",
      "url": "#"
    }, 
    {
      "title": "",
      "url": "#"
    },    {
      "title": "",
      "url": "#"
    }, 
    {
      "title": "",
      "url": "#"
    },    {
      "title": "",
      "url": "#"
    }, 
    {
      "title": "",
      "url": "#"
    },    {
      "title": "",
      "url": "#"
    }, 
    {
      "title": "",
      "url": "#"
    },    {
      "title": "",
      "url": "#"
    }, 
    {
      "title": "",
      "url": "#"
    },    {
      "title": "",
      "url": "#"
    }, 
    {
      "title": "",
      "url": "#"
    },    {
      "title": "",
      "url": "#"
    }, 
    {
      "title": "",
      "url": "#"
    },    {
      "title": "",
      "url": "#"
    }, 
    {
      "title": "",
      "url": "#"
    },    {
      "title": "",
      "url": "#"
    }, 
    {
      "title": "",
      "url": "#"
    },    {
      "title": "",
      "url": "#"
    }, 
    {
      "title": "",
      "url": "#"
    },    {
      "title": "",
      "url": "#"
    }, 
    {
      "title": "",
      "url": "#"
    },    {
      "title": "",
      "url": "#"
    }, 
    {
      "title": "",
      "url": "#"
    },
    {
      "title": "",
      "url": "#"
    }
  ]
} 